GeeksforgeeksCompilerDesignLectureNotes/README.md
GeeksforgeeksCompilerDesignLectureNotes/__init__.py
GeeksforgeeksCompilerDesignLectureNotes/__main__.py
GeeksforgeeksCompilerDesignLectureNotes/file.epub
GeeksforgeeksCompilerDesignLectureNotes/index.html
GeeksforgeeksCompilerDesignLectureNotes/css/__init__.py
GeeksforgeeksCompilerDesignLectureNotes/css/annotations.css
GeeksforgeeksCompilerDesignLectureNotes/css/main.css
GeeksforgeeksCompilerDesignLectureNotes/css/normalize.css
GeeksforgeeksCompilerDesignLectureNotes/css/popup.css
GeeksforgeeksCompilerDesignLectureNotes/font/__init__.py
GeeksforgeeksCompilerDesignLectureNotes/font/fontello.eot
GeeksforgeeksCompilerDesignLectureNotes/font/fontello.svg
GeeksforgeeksCompilerDesignLectureNotes/font/fontello.ttf
GeeksforgeeksCompilerDesignLectureNotes/font/fontello.woff
GeeksforgeeksCompilerDesignLectureNotes/img/__init__.py
GeeksforgeeksCompilerDesignLectureNotes/img/annotator-glyph-sprite.png
GeeksforgeeksCompilerDesignLectureNotes/img/annotator-icon-sprite.png
GeeksforgeeksCompilerDesignLectureNotes/img/apple-touch-icon.png
GeeksforgeeksCompilerDesignLectureNotes/img/cancelfullscreen.png
GeeksforgeeksCompilerDesignLectureNotes/img/close.png
GeeksforgeeksCompilerDesignLectureNotes/img/fullscreen.png
GeeksforgeeksCompilerDesignLectureNotes/img/loader.gif
GeeksforgeeksCompilerDesignLectureNotes/img/menu-icon.png
GeeksforgeeksCompilerDesignLectureNotes/img/save.png
GeeksforgeeksCompilerDesignLectureNotes/img/saved.png
GeeksforgeeksCompilerDesignLectureNotes/img/settings-s.png
GeeksforgeeksCompilerDesignLectureNotes/img/settings.png
GeeksforgeeksCompilerDesignLectureNotes/img/star.png
GeeksforgeeksCompilerDesignLectureNotes/js/__init__.py
GeeksforgeeksCompilerDesignLectureNotes/js/epub.js
GeeksforgeeksCompilerDesignLectureNotes/js/epub.min.js
GeeksforgeeksCompilerDesignLectureNotes/js/epub.min.map
GeeksforgeeksCompilerDesignLectureNotes/js/hooks.min.js
GeeksforgeeksCompilerDesignLectureNotes/js/hooks.min.map
geeksforgeeks_compiler_design_lecture_notes-2024.3.3.0.dist-info/METADATA
geeksforgeeks_compiler_design_lecture_notes-2024.3.3.0.dist-info/WHEEL
geeksforgeeks_compiler_design_lecture_notes-2024.3.3.0.dist-info/entry_points.txt
geeksforgeeks_compiler_design_lecture_notes-2024.3.3.0.dist-info/top_level.txt
geeksforgeeks_compiler_design_lecture_notes-2024.3.3.0.dist-info/RECORD
